napari_z_plotter/__init__.py
napari_z_plotter/_version.py
napari_z_plotter/_widget.py
napari_z_plotter/napari.yaml
napari_z_plotter-0.0.7.dist-info/licenses/LICENSE
napari_z_plotter-0.0.7.dist-info/METADATA
napari_z_plotter-0.0.7.dist-info/WHEEL
napari_z_plotter-0.0.7.dist-info/entry_points.txt
napari_z_plotter-0.0.7.dist-info/top_level.txt
napari_z_plotter-0.0.7.dist-info/RECORD
