Metadata-Version: 2.4
Name: napari-z-plotter
Version: 0.0.7
Summary: A simple utility to interactively plot intensity profiles along the third axis (channel, or Z) of a 3D image while in 2D view.
Author-email: EPFL <imaging@epfl.ch>
License: Copyright (c) 2024, EPFL
Project-URL: homepage, https://github.com/EPFL-Center-for-Imaging/napari-z-plotter.git
Project-URL: repository, https://github.com/EPFL-Center-for-Imaging/napari-z-plotter.git
Classifier: Development Status :: 2 - Pre-Alpha
Classifier: License :: OSI Approved :: BSD License
Classifier: Programming Language :: Python :: 3
Classifier: Programming Language :: Python :: 3.9
Classifier: Programming Language :: Python :: 3.10
Classifier: Programming Language :: Python :: 3.11
Classifier: Programming Language :: Python :: 3.12
Classifier: Programming Language :: Python :: 3.13
Classifier: Topic :: Scientific/Engineering :: Image Processing
Requires-Python: >=3.9
License-File: LICENSE
Requires-Dist: napari[all]>=0.4.16
Requires-Dist: qtpy
Requires-Dist: matplotlib
Dynamic: license-file
